fstmorph/__init__.py
fstmorph/assets/compile_fst.xfst
fstmorph/assets/delete_alt_tag.xfst
fstmorph/csv2lexc.py
fstmorph/extract_tag_combinations.py
fstmorph/src/__init__.py
fstmorph/src/lexc_comment.py
fstmorph/src/lexc_path.py
fstmorph/src/lexicon.py
fstmorph/src/log.py
fstmorph/src/templates.py
fstmorph/tests/README.md
fstmorph/tests/create_yaml.py
fstmorph/tests/run_yaml_tests.py
fstmorph/tests/summarize_tests.py
fstmorph-0.1.1.dist-info/LICENSE.md
fstmorph-0.1.1.dist-info/METADATA
fstmorph-0.1.1.dist-info/WHEEL
fstmorph-0.1.1.dist-info/RECORD
