Metadata-Version: 2.3
Name: FSTmorph
Version: 0.1.1
Summary: 
Author: Miikka Silfverberg
Author-email: msilfver@mail.ubc.ca
Requires-Python: >=3.9,<4.0
Classifier: Programming Language :: Python :: 3
Classifier: Programming Language :: Python :: 3.9
Classifier: Programming Language :: Python :: 3.10
Classifier: Programming Language :: Python :: 3.11
Classifier: Programming Language :: Python :: 3.12
Classifier: Programming Language :: Python :: 3.13
Requires-Dist: PyYAML (>6.0)
Requires-Dist: click (>=8.1.3)
Requires-Dist: jinja2 (>=3.1.3)
Requires-Dist: pandas (>=2.0.1)
